{
    "prepare_queue": {
        "installed": [],
        "uninstalled": []
    },
    "config_munge": {
        "files": {}
    },
    "installed_plugins": {
        "cordova-plugin-console": {
            "PACKAGE_NAME": "sg.beeline.driver"
        },
        "cordova-plugin-device": {
            "PACKAGE_NAME": "sg.beeline.driver"
        },
        "cordova-plugin-geolocation": {
            "PACKAGE_NAME": "sg.beeline.driver"
        },
        "cordova-plugin-splashscreen": {
            "PACKAGE_NAME": "sg.beeline.driver"
        },
        "cordova-plugin-statusbar": {
            "PACKAGE_NAME": "sg.beeline.driver"
        },
        "cordova-plugin-tts": {
            "PACKAGE_NAME": "sg.beeline.driver"
        },
        "cordova-plugin-whitelist": {
            "PACKAGE_NAME": "sg.beeline.driver"
        },
        "ionic-plugin-keyboard": {
            "PACKAGE_NAME": "sg.beeline.driver"
        },
        "cordova-plugin-app-version": {
            "PACKAGE_NAME": "sg.beeline.driver"
        },
        "cordova-plugin-insomnia": {
            "PACKAGE_NAME": "sg.beeline.driver"
        }
    },
    "dependent_plugins": {}
}